platinumtools/__init__.py
platinumtools/dda_constants.py
platinumtools/dda_models-legacy.py
platinumtools/dda_models.py
platinumtools/etl_functions.py
platinumtools/help.py
platinumtools/aws_classes/CommonProcesor.py
platinumtools/aws_classes/JobListener.py
platinumtools/aws_classes/__init__.py
platinumtools/aws_classes/class_adapters.py
platinumtools/aws_classes/class_enhancement-legacy.py
platinumtools/aws_classes/class_enhancement.py
platinumtools/aws_classes/class_guardian.py
platinumtools/aws_classes/class_helpers.py
platinumtools/aws_classes/class_scheduling.py
platinumtools/aws_classes/config_mapper.py
platinumtools/aws_classes/config_mapper_df.py
platinumtools/aws_classes/config_mapper_df_legacy.py
platinumtools/aws_classes/test_common_processing.py
test_scenarios/JobListener.py
test_scenarios/__init__.py
test_scenarios/event-data-into-timeslots.py
test_scenarios/test_adapters.py
test_scenarios/test_code.py
test_scenarios/test_common_processing.py
test_scenarios/test_enhancement.py
test_scenarios/test_event_normalization.py
test_scenarios/test_guardian.py
test_scenarios/test_helpers.py
test_scenarios/test_scheduling.py
test_scenarios/test_splitting_algorthm.py
platinumtools-0.4.5.dist-info/LICENSE
platinumtools-0.4.5.dist-info/METADATA
platinumtools-0.4.5.dist-info/WHEEL
platinumtools-0.4.5.dist-info/top_level.txt
platinumtools-0.4.5.dist-info/RECORD
